binance_data_processor/__init__.py
binance_data_processor/cloud_storage_clients/__init__.py
binance_data_processor/cloud_storage_clients/b2_client.py
binance_data_processor/cloud_storage_clients/s3_client.py
binance_data_processor/core/__init__.py
binance_data_processor/core/abstract_base_classes.py
binance_data_processor/core/blackout_supervisor.py
binance_data_processor/core/command_line_interface.py
binance_data_processor/core/difference_depth_queue.py
binance_data_processor/core/exceptions.py
binance_data_processor/core/fastapi_manager.py
binance_data_processor/core/listener_observer_updater.py
binance_data_processor/core/load_config.py
binance_data_processor/core/logo.py
binance_data_processor/core/queue_pool.py
binance_data_processor/core/setup_logger.py
binance_data_processor/core/snapshot_manager.py
binance_data_processor/core/spinning_donut.py
binance_data_processor/core/stream_data_saver_and_sender.py
binance_data_processor/core/stream_listener.py
binance_data_processor/core/stream_listener_id.py
binance_data_processor/core/stream_service.py
binance_data_processor/core/timestamps_generator.py
binance_data_processor/core/trade_queue.py
binance_data_processor/core/url_factory.py
binance_data_processor/data_sink/__init__.py
binance_data_processor/data_sink/data_sink_facade.py
binance_data_processor/data_sink/main_data_sink.py
binance_data_processor/enums/__init__.py
binance_data_processor/enums/asset_parameters.py
binance_data_processor/enums/commands_registry_enum.py
binance_data_processor/enums/data_quality_report_status_enum.py
binance_data_processor/enums/data_save_target_enum.py
binance_data_processor/enums/data_sink_config.py
binance_data_processor/enums/epoch_time_unit.py
binance_data_processor/enums/instruments_matrix.py
binance_data_processor/enums/interval_settings.py
binance_data_processor/enums/market_enum.py
binance_data_processor/enums/storage_connection_parameters.py
binance_data_processor/enums/stream_type_enum.py
binance_data_processor-0.0.1.dist-info/METADATA
binance_data_processor-0.0.1.dist-info/WHEEL
binance_data_processor-0.0.1.dist-info/top_level.txt
binance_data_processor-0.0.1.dist-info/RECORD
