Metadata-Version: 2.4
Name: binance-data-processor
Version: 0.0.1
Summary: A package for archiving Binance data
Home-page: https://www.youtube.com/watch?v=dQw4w9WgXcQ
Author: Daniel Lasota
Author-email: grossmann.root@gmail.com
Keywords: binance data processor listener archiver quant data sprzedam opla
Requires-Python: >=3.11
Requires-Dist: python-dotenv
Requires-Dist: fastapi
Requires-Dist: uvicorn
Requires-Dist: websockets
Requires-Dist: orjson
Requires-Dist: requests
Requires-Dist: numpy
Requires-Dist: pandas
Requires-Dist: boto3==1.35.2
Requires-Dist: alive-progress
Provides-Extra: dev
Requires-Dist: pytest; extra == "dev"
Requires-Dist: objgraph; extra == "dev"
Requires-Dist: pympler; extra == "dev"
Provides-Extra: azure
Requires-Dist: azure-identity; extra == "azure"
Requires-Dist: azure-storage-blob; extra == "azure"
Dynamic: author
Dynamic: author-email
Dynamic: description
Dynamic: description-content-type
Dynamic: home-page
Dynamic: keywords
Dynamic: provides-extra
Dynamic: requires-dist
Dynamic: requires-python
Dynamic: summary
